csvtoparquet/__init__.py
csvtoparquet/__main__.py
csvtoparquet/cli_commands.py
csvtoparquet/commands.py
csvtoparquet/connect.py
csvtoparquet/convert_module.py
csvtoparquet/converter.py
csvtoparquet/helpers.py
csvtoparquet/object_module.py
csvtoparquet/options.py
csvtoparquet-0.1.5.dist-info/METADATA
csvtoparquet-0.1.5.dist-info/RECORD
csvtoparquet-0.1.5.dist-info/WHEEL
csvtoparquet-0.1.5.dist-info/entry_points.txt
csvtoparquet-0.1.5.dist-info/top_level.txt
