Metadata-Version: 2.1
Name: csvtoparquet
Version: 0.1.5
Summary: UNKNOWN
Home-page: UNKNOWN
Author: IBM
Author-email: abdullah.alger@ibm.com
License: Apache 2.0
Keywords: cloud csv parquet object_storage IBM
Platform: UNKNOWN
Classifier: Development Status :: 3 - Alpha
Classifier: License :: OSI Approved :: Apache Software License
Classifier: Programming Language :: Python :: 3.6
Classifier: Topic :: Software Development :: Libraries :: Python Modules
Classifier: Intended Audience :: Developers
Classifier: Natural Language :: English
Requires-Dist: pandas
Requires-Dist: pyarrow
Requires-Dist: ibm-cos-sdk
Requires-Dist: simplejson
